[
  {
    "ID": 1,
    "Word": "ألف",
    "Type": "اسم",
    "Category": "اسم حرف ابجدي"
  },
  {
    "ID": 2,
    "Word": "باء",
    "Type": "اسم",
    "Category": "اسم حرف ابجدي"
  },
  {
    "ID": 3,
    "Word": "تاء",
    "Type": "اسم",
    "Category": "اسم حرف ابجدي"
  },
  {
    "ID": 4,
    "Word": "ثاء",
    "Type": "اسم",
    "Category": "اسم حرف ابجدي"
  },
  {
    "ID": 5,
    "Word": "جيم",
    "Type": "اسم",
    "Category": "اسم حرف ابجدي"
  },
  {
    "ID": 6,
    "Word": "حاء",
    "Type": "اسم",
    "Category": "اسم حرف ابجدي"
  },
  {
    "ID": 7,
    "Word": "خاء",
    "Type": "اسم",
    "Category": "اسم حرف ابجدي"
  },
  {
    "ID": 8,
    "Word": "دال",
    "Type": "اسم",
    "Category": "اسم حرف ابجدي"
  },
  {
    "ID": 9,
    "Word": "ذال",
    "Type": "اسم",
    "Category": "اسم حرف ابجدي"
  },
  {
    "ID": 10,
    "Word": "راء",
    "Type": "اسم",
    "Category": "اسم حرف ابجدي"
  },
  {
    "ID": 11,
    "Word": "زاي",
    "Type": "اسم",
    "Category": "اسم حرف ابجدي"
  },
  {
    "ID": 12,
    "Word": "سين",
    "Type": "اسم",
    "Category": "اسم حرف ابجدي"
  },
  {
    "ID": 13,
    "Word": "شين",
    "Type": "اسم",
    "Category": "اسم حرف ابجدي"
  },
  {
    "ID": 14,
    "Word": "صاد",
    "Type": "اسم",
    "Category": "اسم حرف ابجدي"
  },
  {
    "ID": 15,
    "Word": "ضاد",
    "Type": "اسم",
    "Category": "اسم حرف ابجدي"
  },
  {
    "ID": 16,
    "Word": "طاء",
    "Type": "اسم",
    "Category": "اسم حرف ابجدي"
  },
  {
    "ID": 17,
    "Word": "ظاء",
    "Type": "اسم",
    "Category": "اسم حرف ابجدي"
  },
  {
    "ID": 18,
    "Word": "عين",
    "Type": "اسم",
    "Category": "اسم حرف ابجدي"
  },
  {
    "ID": 19,
    "Word": "غين",
    "Type": "اسم",
    "Category": "اسم حرف ابجدي"
  },
  {
    "ID": 20,
    "Word": "فاء",
    "Type": "اسم",
    "Category": "اسم حرف ابجدي"
  },
  {
    "ID": 21,
    "Word": "قاف",
    "Type": "اسم",
    "Category": "اسم حرف ابجدي"
  },
  {
    "ID": 22,
    "Word": "كاف",
    "Type": "اسم",
    "Category": "اسم حرف ابجدي"
  },
  {
    "ID": 23,
    "Word": "لام",
    "Type": "اسم",
    "Category": "اسم حرف ابجدي"
  },
  {
    "ID": 24,
    "Word": "ميم",
    "Type": "اسم",
    "Category": "اسم حرف ابجدي"
  },
  {
    "ID": 25,
    "Word": "نون",
    "Type": "اسم",
    "Category": "اسم حرف ابجدي"
  },
  {
    "ID": 26,
    "Word": "هاء",
    "Type": "اسم",
    "Category": "اسم حرف ابجدي"
  },
  {
    "ID": 27,
    "Word": "همزة",
    "Type": "اسم",
    "Category": "اسم حرف ابجدي"
  },
  {
    "ID": 28,
    "Word": "واو",
    "Type": "اسم",
    "Category": "اسم حرف ابجدي"
  },
  {
    "ID": 29,
    "Word": "ياء",
    "Type": "اسم",
    "Category": "اسم حرف ابجدي"
  },
  {
    "ID": 30,
    "Word": "آب",
    "Type": "اسم",
    "Category": "اسم شهر"
  },
  {
    "ID": 31,
    "Word": "آذار",
    "Type": "اسم",
    "Category": "اسم شهر"
  },
  {
    "ID": 32,
    "Word": "أبريل",
    "Type": "اسم",
    "Category": "اسم شهر"
  },
  {
    "ID": 33,
    "Word": "أغسطس",
    "Type": "اسم",
    "Category": "اسم شهر"
  },
  {
    "ID": 34,
    "Word": "أفريل",
    "Type": "اسم",
    "Category": "اسم شهر"
  },
  {
    "ID": 35,
    "Word": "أكتوبر",
    "Type": "اسم",
    "Category": "اسم شهر"
  },
  {
    "ID": 36,
    "Word": "أوت",
    "Type": "اسم",
    "Category": "اسم شهر"
  },
  {
    "ID": 37,
    "Word": "أيار",
    "Type": "اسم",
    "Category": "اسم شهر"
  },
  {
    "ID": 38,
    "Word": "أيلول",
    "Type": "اسم",
    "Category": "اسم شهر"
  },
  {
    "ID": 39,
    "Word": "تشرين",
    "Type": "اسم",
    "Category": "اسم شهر"
  },
  {
    "ID": 40,
    "Word": "تموز",
    "Type": "اسم",
    "Category": "اسم شهر"
  },
  {
    "ID": 41,
    "Word": "جانفي",
    "Type": "اسم",
    "Category": "اسم شهر"
  },
  {
    "ID": 42,
    "Word": "جوان",
    "Type": "اسم",
    "Category": "اسم شهر"
  },
  {
    "ID": 43,
    "Word": "جويلية",
    "Type": "اسم",
    "Category": "اسم شهر"
  },
  {
    "ID": 44,
    "Word": "حزيران",
    "Type": "اسم",
    "Category": "اسم شهر"
  },
  {
    "ID": 45,
    "Word": "ديسمبر",
    "Type": "اسم",
    "Category": "اسم شهر"
  },
  {
    "ID": 46,
    "Word": "سبتمبر",
    "Type": "اسم",
    "Category": "اسم شهر"
  },
  {
    "ID": 47,
    "Word": "شباط",
    "Type": "اسم",
    "Category": "اسم شهر"
  },
  {
    "ID": 48,
    "Word": "فبراير",
    "Type": "اسم",
    "Category": "اسم شهر"
  },
  {
    "ID": 49,
    "Word": "فيفري",
    "Type": "اسم",
    "Category": "اسم شهر"
  },
  {
    "ID": 50,
    "Word": "كانون",
    "Type": "اسم",
    "Category": "اسم شهر"
  },
  {
    "ID": 51,
    "Word": "مارس",
    "Type": "اسم",
    "Category": "اسم شهر"
  },
  {
    "ID": 52,
    "Word": "مارس",
    "Type": "اسم",
    "Category": "اسم شهر"
  },
  {
    "ID": 53,
    "Word": "ماي",
    "Type": "اسم",
    "Category": "اسم شهر"
  },
  {
    "ID": 54,
    "Word": "مايو",
    "Type": "اسم",
    "Category": "اسم شهر"
  },
  {
    "ID": 55,
    "Word": "نوفمبر",
    "Type": "اسم",
    "Category": "اسم شهر"
  },
  {
    "ID": 56,
    "Word": "نيسان",
    "Type": "اسم",
    "Category": "اسم شهر"
  },
  {
    "ID": 57,
    "Word": "يناير",
    "Type": "اسم",
    "Category": "اسم شهر"
  },
  {
    "ID": 58,
    "Word": "يوليو",
    "Type": "اسم",
    "Category": "اسم شهر"
  },
  {
    "ID": 59,
    "Word": "يونيو",
    "Type": "اسم",
    "Category": "اسم شهر"
  },
  {
    "ID": 60,
    "Word": "اثنا",
    "Type": "اسم",
    "Category": "اسم عدد"
  },
  {
    "ID": 61,
    "Word": "اثنان",
    "Type": "اسم",
    "Category": "اسم عدد"
  },
  {
    "ID": 62,
    "Word": "اثني",
    "Type": "اسم",
    "Category": "اسم عدد"
  },
  {
    "ID": 63,
    "Word": "اربعون",
    "Type": "اسم",
    "Category": "اسم عدد"
  },
  {
    "ID": 64,
    "Word": "اربعين",
    "Type": "اسم",
    "Category": "اسم عدد"
  },
  {
    "ID": 65,
    "Word": "أحد",
    "Type": "اسم",
    "Category": "اسم عدد"
  },
  {
    "ID": 66,
    "Word": "أربع",
    "Type": "اسم",
    "Category": "اسم عدد"
  },
  {
    "ID": 67,
    "Word": "أربعة",
    "Type": "اسم",
    "Category": "اسم عدد"
  },
  {
    "ID": 68,
    "Word": "أربعمئة",
    "Type": "اسم",
    "Category": "اسم عدد"
  },
  {
    "ID": 69,
    "Word": "أربعمائة",
    "Type": "اسم",
    "Category": "اسم عدد"
  },
  {
    "ID": 70,
    "Word": "إحدى",
    "Type": "اسم",
    "Category": "اسم عدد"
  },
  {
    "ID": 71,
    "Word": "بضع",
    "Type": "اسم",
    "Category": "اسم عدد"
  },
  {
    "ID": 72,
    "Word": "تسع",
    "Type": "اسم",
    "Category": "اسم عدد"
  },
  {
    "ID": 73,
    "Word": "تسعة",
    "Type": "اسم",
    "Category": "اسم عدد"
  },
  {
    "ID": 74,
    "Word": "تسعمئة",
    "Type": "اسم",
    "Category": "اسم عدد"
  },
  {
    "ID": 75,
    "Word": "تسعمائة",
    "Type": "اسم",
    "Category": "اسم عدد"
  },
  {
    "ID": 76,
    "Word": "تسعون",
    "Type": "اسم",
    "Category": "اسم عدد"
  },
  {
    "ID": 77,
    "Word": "تسعين",
    "Type": "اسم",
    "Category": "اسم عدد"
  },
  {
    "ID": 78,
    "Word": "ثلاث",
    "Type": "اسم",
    "Category": "اسم عدد"
  },
  {
    "ID": 79,
    "Word": "ثلاثة",
    "Type": "اسم",
    "Category": "اسم عدد"
  },
  {
    "ID": 80,
    "Word": "ثلاثمئة",
    "Type": "اسم",
    "Category": "اسم عدد"
  },
  {
    "ID": 81,
    "Word": "ثلاثمائة",
    "Type": "اسم",
    "Category": "اسم عدد"
  },
  {
    "ID": 82,
    "Word": "ثلاثون",
    "Type": "اسم",
    "Category": "اسم عدد"
  },
  {
    "ID": 83,
    "Word": "ثلاثين",
    "Type": "اسم",
    "Category": "اسم عدد"
  },
  {
    "ID": 84,
    "Word": "ثمان",
    "Type": "اسم",
    "Category": "اسم عدد"
  },
  {
    "ID": 85,
    "Word": "ثمانمئة",
    "Type": "اسم",
    "Category": "اسم عدد"
  },
  {
    "ID": 86,
    "Word": "ثمانون",
    "Type": "اسم",
    "Category": "اسم عدد"
  },
  {
    "ID": 87,
    "Word": "ثماني",
    "Type": "اسم",
    "Category": "اسم عدد"
  },
  {
    "ID": 88,
    "Word": "ثمانية",
    "Type": "اسم",
    "Category": "اسم عدد"
  },
  {
    "ID": 89,
    "Word": "ثمانين",
    "Type": "اسم",
    "Category": "اسم عدد"
  },
  {
    "ID": 90,
    "Word": "ثمنمئة",
    "Type": "اسم",
    "Category": "اسم عدد"
  },
  {
    "ID": 91,
    "Word": "خمس",
    "Type": "اسم",
    "Category": "اسم عدد"
  },
  {
    "ID": 92,
    "Word": "خمسة",
    "Type": "اسم",
    "Category": "اسم عدد"
  },
  {
    "ID": 93,
    "Word": "خمسمئة",
    "Type": "اسم",
    "Category": "اسم عدد"
  },
  {
    "ID": 94,
    "Word": "خمسمائة",
    "Type": "اسم",
    "Category": "اسم عدد"
  },
  {
    "ID": 95,
    "Word": "خمسون",
    "Type": "اسم",
    "Category": "اسم عدد"
  },
  {
    "ID": 96,
    "Word": "خمسين",
    "Type": "اسم",
    "Category": "اسم عدد"
  },
  {
    "ID": 97,
    "Word": "سبع",
    "Type": "اسم",
    "Category": "اسم عدد"
  },
  {
    "ID": 98,
    "Word": "سبعة",
    "Type": "اسم",
    "Category": "اسم عدد"
  },
  {
    "ID": 99,
    "Word": "سبعمئة",
    "Type": "اسم",
    "Category": "اسم عدد"
  },
  {
    "ID": 100,
    "Word": "سبعمائة",
    "Type": "اسم",
    "Category": "اسم عدد"
  },
  {
    "ID": 101,
    "Word": "سبعون",
    "Type": "اسم",
    "Category": "اسم عدد"
  },
  {
    "ID": 102,
    "Word": "سبعين",
    "Type": "اسم",
    "Category": "اسم عدد"
  },
  {
    "ID": 103,
    "Word": "ست",
    "Type": "اسم",
    "Category": "اسم عدد"
  },
  {
    "ID": 104,
    "Word": "ستة",
    "Type": "اسم",
    "Category": "اسم عدد"
  },
  {
    "ID": 105,
    "Word": "ستمئة",
    "Type": "اسم",
    "Category": "اسم عدد"
  },
  {
    "ID": 106,
    "Word": "ستمائة",
    "Type": "اسم",
    "Category": "اسم عدد"
  },
  {
    "ID": 107,
    "Word": "ستون",
    "Type": "اسم",
    "Category": "اسم عدد"
  },
  {
    "ID": 108,
    "Word": "ستين",
    "Type": "اسم",
    "Category": "اسم عدد"
  },
  {
    "ID": 109,
    "Word": "عشر",
    "Type": "اسم",
    "Category": "اسم عدد"
  },
  {
    "ID": 110,
    "Word": "عشرة",
    "Type": "اسم",
    "Category": "اسم عدد"
  },
  {
    "ID": 111,
    "Word": "عشرون",
    "Type": "اسم",
    "Category": "اسم عدد"
  },
  {
    "ID": 112,
    "Word": "عشرين",
    "Type": "اسم",
    "Category": "اسم عدد"
  },
  {
    "ID": 113,
    "Word": "مئة",
    "Type": "اسم",
    "Category": "اسم عدد"
  },
  {
    "ID": 114,
    "Word": "مئتان",
    "Type": "اسم",
    "Category": "اسم عدد"
  },
  {
    "ID": 115,
    "Word": "مئتين",
    "Type": "اسم",
    "Category": "اسم عدد"
  },
  {
    "ID": 116,
    "Word": "مائة",
    "Type": "اسم",
    "Category": "اسم عدد"
  },
  {
    "ID": 117,
    "Word": "نيف",
    "Type": "اسم",
    "Category": "اسم عدد"
  },
  {
    "ID": 118,
    "Word": "واحد",
    "Type": "اسم",
    "Category": "اسم عدد"
  },
  {
    "ID": 119,
    "Word": "أول",
    "Type": "اسم",
    "Category": "اسم عدد ترتيب"
  },
  {
    "ID": 120,
    "Word": "تاسع",
    "Type": "اسم",
    "Category": "اسم عدد ترتيب"
  },
  {
    "ID": 121,
    "Word": "ثالث",
    "Type": "اسم",
    "Category": "اسم عدد ترتيب"
  },
  {
    "ID": 122,
    "Word": "ثامن",
    "Type": "اسم",
    "Category": "اسم عدد ترتيب"
  },
  {
    "ID": 123,
    "Word": "ثان",
    "Type": "اسم",
    "Category": "اسم عدد ترتيب"
  },
  {
    "ID": 124,
    "Word": "ثاني",
    "Type": "اسم",
    "Category": "اسم عدد ترتيب"
  },
  {
    "ID": 125,
    "Word": "حادي",
    "Type": "اسم",
    "Category": "اسم عدد ترتيب"
  },
  {
    "ID": 126,
    "Word": "خامس",
    "Type": "اسم",
    "Category": "اسم عدد ترتيب"
  },
  {
    "ID": 127,
    "Word": "رابع",
    "Type": "اسم",
    "Category": "اسم عدد ترتيب"
  },
  {
    "ID": 128,
    "Word": "سابع",
    "Type": "اسم",
    "Category": "اسم عدد ترتيب"
  },
  {
    "ID": 129,
    "Word": "سادس",
    "Type": "اسم",
    "Category": "اسم عدد ترتيب"
  },
  {
    "ID": 130,
    "Word": "عاشر",
    "Type": "اسم",
    "Category": "اسم عدد ترتيب"
  },
  {
    "ID": 131,
    "Word": "جنيه",
    "Type": "اسم",
    "Category": "اسم عملة"
  },
  {
    "ID": 132,
    "Word": "درهم",
    "Type": "اسم",
    "Category": "اسم عملة"
  },
  {
    "ID": 133,
    "Word": "دولار",
    "Type": "اسم",
    "Category": "اسم عملة"
  },
  {
    "ID": 134,
    "Word": "دينار",
    "Type": "اسم",
    "Category": "اسم عملة"
  },
  {
    "ID": 135,
    "Word": "ريال",
    "Type": "اسم",
    "Category": "اسم عملة"
  },
  {
    "ID": 136,
    "Word": "سنتيم",
    "Type": "اسم",
    "Category": "اسم عملة"
  },
  {
    "ID": 137,
    "Word": "شيكل",
    "Type": "اسم",
    "Category": "اسم عملة"
  },
  {
    "ID": 138,
    "Word": "فلس",
    "Type": "اسم",
    "Category": "اسم عملة"
  },
  {
    "ID": 139,
    "Word": "قرش",
    "Type": "اسم",
    "Category": "اسم عملة"
  },
  {
    "ID": 140,
    "Word": "ليرة",
    "Type": "اسم",
    "Category": "اسم عملة"
  },
  {
    "ID": 141,
    "Word": "مليم",
    "Type": "اسم",
    "Category": "اسم عملة"
  },
  {
    "ID": 142,
    "Word": "هللة",
    "Type": "اسم",
    "Category": "اسم عملة"
  },
  {
    "ID": 143,
    "Word": "ين",
    "Type": "اسم",
    "Category": "اسم عملة"
  },
  {
    "ID": 144,
    "Word": "يوان",
    "Type": "اسم",
    "Category": "اسم عملة"
  },
  {
    "ID": 145,
    "Word": "يورو",
    "Type": "اسم",
    "Category": "اسم عملة"
  },
  {
    "ID": 146,
    "Word": "اثنين",
    "Type": "اسم",
    "Category": "اسم يوم"
  },
  {
    "ID": 147,
    "Word": "أحد",
    "Type": "اسم",
    "Category": "اسم يوم"
  },
  {
    "ID": 148,
    "Word": "أربعاء",
    "Type": "اسم",
    "Category": "اسم يوم"
  },
  {
    "ID": 149,
    "Word": "ثلاثاء",
    "Type": "اسم",
    "Category": "اسم يوم"
  },
  {
    "ID": 150,
    "Word": "جمعة",
    "Type": "اسم",
    "Category": "اسم يوم"
  },
  {
    "ID": 151,
    "Word": "خميس",
    "Type": "اسم",
    "Category": "اسم يوم"
  },
  {
    "ID": 152,
    "Word": "سبت",
    "Type": "اسم",
    "Category": "اسم يوم"
  },
  {
    "ID": 153,
    "Word": "أسكن",
    "Type": "فعل",
    "Category": "متعدية 2 م به"
  },
  {
    "ID": 154,
    "Word": "أطعم",
    "Type": "فعل",
    "Category": "متعدية 2 م به"
  },
  {
    "ID": 155,
    "Word": "أعطى",
    "Type": "فعل",
    "Category": "متعدية 2 م به"
  },
  {
    "ID": 156,
    "Word": "رزق",
    "Type": "فعل",
    "Category": "متعدية 2 م به"
  },
  {
    "ID": 157,
    "Word": "زود",
    "Type": "فعل",
    "Category": "متعدية 2 م به"
  },
  {
    "ID": 158,
    "Word": "سقى",
    "Type": "فعل",
    "Category": "متعدية 2 م به"
  },
  {
    "ID": 159,
    "Word": "كسا",
    "Type": "فعل",
    "Category": "متعدية 2 م به"
  },
  {
    "ID": 160,
    "Word": "أخبر",
    "Type": "فعل",
    "Category": "متعدية 3 م به"
  },
  {
    "ID": 161,
    "Word": "أرى",
    "Type": "فعل",
    "Category": "متعدية 3 م به"
  },
  {
    "ID": 162,
    "Word": "أعلم",
    "Type": "فعل",
    "Category": "متعدية 3 م به"
  },
  {
    "ID": 163,
    "Word": "أنبأ",
    "Type": "فعل",
    "Category": "متعدية 3 م به"
  },
  {
    "ID": 164,
    "Word": "حدَث",
    "Type": "فعل",
    "Category": "متعدية 3 م به"
  },
  {
    "ID": 165,
    "Word": "خبَّر",
    "Type": "فعل",
    "Category": "متعدية 3 م به"
  },
  {
    "ID": 166,
    "Word": "نبَّا",
    "Type": "فعل",
    "Category": "متعدية 3 م به"
  },
  {
    "ID": 167,
    "Word": "اتخذ",
    "Type": "فعل",
    "Category": "أفعال قلوب"
  },
  {
    "ID": 168,
    "Word": "ألفى",
    "Type": "فعل",
    "Category": "أفعال قلوب"
  },
  {
    "ID": 169,
    "Word": "تخذ",
    "Type": "فعل",
    "Category": "أفعال قلوب"
  },
  {
    "ID": 170,
    "Word": "ترك",
    "Type": "فعل",
    "Category": "أفعال قلوب"
  },
  {
    "ID": 171,
    "Word": "تعلَّم",
    "Type": "فعل",
    "Category": "أفعال قلوب"
  },
  {
    "ID": 172,
    "Word": "جعل",
    "Type": "فعل",
    "Category": "أفعال قلوب"
  },
  {
    "ID": 173,
    "Word": "حجا",
    "Type": "فعل",
    "Category": "أفعال قلوب"
  },
  {
    "ID": 174,
    "Word": "حسب",
    "Type": "فعل",
    "Category": "أفعال قلوب"
  },
  {
    "ID": 175,
    "Word": "حسب",
    "Type": "فعل",
    "Category": "أفعال قلوب"
  },
  {
    "ID": 176,
    "Word": "خال",
    "Type": "فعل",
    "Category": "أفعال قلوب"
  },
  {
    "ID": 177,
    "Word": "خال",
    "Type": "فعل",
    "Category": "أفعال قلوب"
  },
  {
    "ID": 178,
    "Word": "درى",
    "Type": "فعل",
    "Category": "أفعال قلوب"
  },
  {
    "ID": 179,
    "Word": "ذهب",
    "Type": "فعل",
    "Category": "أفعال قلوب"
  },
  {
    "ID": 180,
    "Word": "رأى",
    "Type": "فعل",
    "Category": "أفعال قلوب"
  },
  {
    "ID": 181,
    "Word": "زعم",
    "Type": "فعل",
    "Category": "أفعال قلوب"
  },
  {
    "ID": 182,
    "Word": "صبر",
    "Type": "فعل",
    "Category": "أفعال قلوب"
  },
  {
    "ID": 183,
    "Word": "ظنَّ",
    "Type": "فعل",
    "Category": "أفعال قلوب"
  },
  {
    "ID": 184,
    "Word": "عدَّ",
    "Type": "فعل",
    "Category": "أفعال قلوب"
  },
  {
    "ID": 185,
    "Word": "علم",
    "Type": "فعل",
    "Category": "أفعال قلوب"
  },
  {
    "ID": 186,
    "Word": "غادر",
    "Type": "فعل",
    "Category": "أفعال قلوب"
  },
  {
    "ID": 187,
    "Word": "وجد",
    "Type": "فعل",
    "Category": "أفعال قلوب"
  },
  {
    "ID": 188,
    "Word": "ورد",
    "Type": "فعل",
    "Category": "أفعال قلوب"
  },
  {
    "ID": 189,
    "Word": "وهب",
    "Type": "فعل",
    "Category": "أفعال قلوب"
  },
  {
    "ID": 190,
    "Word": "أصلا",
    "Type": "اسم",
    "Category": "المنصوبات"
  },
  {
    "ID": 191,
    "Word": "أهلا",
    "Type": "اسم",
    "Category": "المنصوبات"
  },
  {
    "ID": 192,
    "Word": "أيضا",
    "Type": "اسم",
    "Category": "المنصوبات"
  },
  {
    "ID": 193,
    "Word": "بؤسا",
    "Type": "اسم",
    "Category": "المنصوبات"
  },
  {
    "ID": 194,
    "Word": "بعدا",
    "Type": "اسم",
    "Category": "المنصوبات"
  },
  {
    "ID": 195,
    "Word": "بغتة",
    "Type": "اسم",
    "Category": "المنصوبات"
  },
  {
    "ID": 196,
    "Word": "تعسا",
    "Type": "اسم",
    "Category": "المنصوبات"
  },
  {
    "ID": 197,
    "Word": "حقا",
    "Type": "اسم",
    "Category": "المنصوبات"
  },
  {
    "ID": 198,
    "Word": "حمدا",
    "Type": "اسم",
    "Category": "المنصوبات"
  },
  {
    "ID": 199,
    "Word": "خاصة",
    "Type": "اسم",
    "Category": "المنصوبات"
  },
  {
    "ID": 200,
    "Word": "خلافا",
    "Type": "اسم",
    "Category": "المنصوبات"
  },
  {
    "ID": 201,
    "Word": "دواليك",
    "Type": "اسم",
    "Category": "المنصوبات"
  },
  {
    "ID": 202,
    "Word": "سحقا",
    "Type": "اسم",
    "Category": "المنصوبات"
  },
  {
    "ID": 203,
    "Word": "سرا",
    "Type": "اسم",
    "Category": "المنصوبات"
  },
  {
    "ID": 204,
    "Word": "سمعا",
    "Type": "اسم",
    "Category": "المنصوبات"
  },
  {
    "ID": 205,
    "Word": "صبرا",
    "Type": "اسم",
    "Category": "المنصوبات"
  },
  {
    "ID": 206,
    "Word": "صدقا",
    "Type": "اسم",
    "Category": "المنصوبات"
  },
  {
    "ID": 207,
    "Word": "صراحة",
    "Type": "اسم",
    "Category": "المنصوبات"
  },
  {
    "ID": 208,
    "Word": "طرا",
    "Type": "اسم",
    "Category": "المنصوبات"
  },
  {
    "ID": 209,
    "Word": "عجبا",
    "Type": "اسم",
    "Category": "المنصوبات"
  },
  {
    "ID": 210,
    "Word": "عيانا",
    "Type": "اسم",
    "Category": "المنصوبات"
  },
  {
    "ID": 211,
    "Word": "غالبا",
    "Type": "اسم",
    "Category": "المنصوبات"
  },
  {
    "ID": 212,
    "Word": "فرادى",
    "Type": "اسم",
    "Category": "المنصوبات"
  },
  {
    "ID": 213,
    "Word": "فضلا",
    "Type": "اسم",
    "Category": "المنصوبات"
  },
  {
    "ID": 214,
    "Word": "قاطبة",
    "Type": "اسم",
    "Category": "المنصوبات"
  },
  {
    "ID": 215,
    "Word": "كَثِيرًا",
    "Type": "اسم",
    "Category": "المنصوبات"
  },
  {
    "ID": 216,
    "Word": "لَبَّيْكَ",
    "Type": "اسم",
    "Category": "المنصوبات"
  },
  {
    "ID": 217,
    "Word": "مَعَاذَ",
    "Type": "اسم",
    "Category": "المنصوبات"
  }
]